{"nodes":[{"id":"js_stars","label":"stars.js","file_type":"code","source_file":"js/stars.js","source_location":"L1"},{"id":"js_stars_resize","label":"resize()","file_type":"code","source_file":"js/stars.js","source_location":"L41"},{"id":"js_stars_mkstar","label":"mkStar()","file_type":"code","source_file":"js/stars.js","source_location":"L46"},{"id":"js_stars_seed","label":"seed()","file_type":"code","source_file":"js/stars.js","source_location":"L61"},{"id":"js_stars_spawnshoot","label":"spawnShoot()","file_type":"code","source_file":"js/stars.js","source_location":"L67"},{"id":"js_stars_draw","label":"draw()","file_type":"code","source_file":"js/stars.js","source_location":"L83"},{"id":"js_stars_setmouse","label":"setMouse()","file_type":"code","source_file":"js/stars.js","source_location":"L192"}],"edges":[{"source":"js_stars","target":"js_stars_resize","relation":"contains","confidence":"EXTRACTED","source_file":"js/stars.js","source_location":"L41","weight":1},{"source":"js_stars","target":"js_stars_mkstar","relation":"contains","confidence":"EXTRACTED","source_file":"js/stars.js","source_location":"L46","weight":1},{"source":"js_stars","target":"js_stars_seed","relation":"contains","confidence":"EXTRACTED","source_file":"js/stars.js","source_location":"L61","weight":1},{"source":"js_stars","target":"js_stars_spawnshoot","relation":"contains","confidence":"EXTRACTED","source_file":"js/stars.js","source_location":"L67","weight":1},{"source":"js_stars","target":"js_stars_draw","relation":"contains","confidence":"EXTRACTED","source_file":"js/stars.js","source_location":"L83","weight":1},{"source":"js_stars","target":"js_stars_setmouse","relation":"contains","confidence":"EXTRACTED","source_file":"js/stars.js","source_location":"L192","weight":1},{"source":"js_stars_seed","target":"js_stars_mkstar","relation":"calls","confidence":"EXTRACTED","source_file":"js/stars.js","source_location":"L63","weight":1},{"source":"js_stars_draw","target":"js_stars_spawnshoot","relation":"calls","confidence":"EXTRACTED","source_file":"js/stars.js","source_location":"L88","weight":1}]}